LICENSE
MANIFEST.in
README.rst
requirements.txt
setup.py
candv_x/__init__.py
candv_x/rest_framework/__init__.py
candv_x/rest_framework/choices/__init__.py
candv_x/rest_framework/choices/fields.py
candv_x/rest_framework/choices/views.py
django_rf_candv_choices.egg-info/PKG-INFO
django_rf_candv_choices.egg-info/SOURCES.txt
django_rf_candv_choices.egg-info/dependency_links.txt
django_rf_candv_choices.egg-info/namespace_packages.txt
django_rf_candv_choices.egg-info/requires.txt
django_rf_candv_choices.egg-info/top_level.txt