Metadata-Version: 1.1
Name: django-rf-candv-choices
Version: 1.0.0
Summary: Support of django-candv-choices for django-rest-framework.
Home-page: https://github.com/oblalex/django-rf-candv-choices
Author: Alexander Oblovatniy
Author-email: oblovatniy@gmail.com
License: LGPLv3
Keywords: choices,constants,candv,values,Django,rest-framework
Platform: any
Classifier: Development Status :: 5 - Production/Stable
Classifier: Intended Audience :: Developers
Classifier: License :: OSI Approved :: GNU Lesser General Public License v3 (LGPLv3)
Classifier: Natural Language :: English
Classifier: Operating System :: OS Independent
Classifier: Programming Language :: Python :: 2.7
Classifier: Programming Language :: Python :: 3.4
Classifier: Topic :: Software Development :: Libraries
